pypestutils.libs/libgfortran-040039e1.so.5.0.0
pypestutils.libs/libquadmath-96973f99.so.0.0.0
pypestutils/ctypes_declarations.py
pypestutils/helpers.py
pypestutils/logger.py
pypestutils/pestutilslib.py
pypestutils/__init__.py
pypestutils/version.py
pypestutils/data.py
pypestutils/enum.py
pypestutils/finder.py
pypestutils/lib/libpestutils.so
pypestutils-0.2.1.dist-info/WHEEL
pypestutils-0.2.1.dist-info/LICENSE
pypestutils-0.2.1.dist-info/top_level.txt
pypestutils-0.2.1.dist-info/METADATA
pypestutils-0.2.1.dist-info/RECORD
