Metadata-Version: 2.1
Name: pypestutils
Version: 0.2.1
Summary: PEST utilities for MODFLOW
Author-email: Jeremy White <jtwhite1000@gmail.com>, Mike Taves <mwtoews@gmail.com>
License: Unlicense
Project-URL: Repository, https://github.com/pypest/pypestutils
Keywords: PEST,MODFLOW,groundwater,model
Classifier: Development Status :: 2 - Pre-Alpha
Classifier: Intended Audience :: Science/Research
Classifier: License :: OSI Approved :: The Unlicense (Unlicense)
Classifier: Operating System :: Unix
Classifier: Operating System :: MacOS
Classifier: Operating System :: Microsoft :: Windows
Classifier: Programming Language :: Fortran
Classifier: Programming Language :: Python :: 3 :: Only
Classifier: Programming Language :: Python :: 3
Classifier: Programming Language :: Python :: 3.8
Classifier: Programming Language :: Python :: 3.9
Classifier: Programming Language :: Python :: 3.10
Classifier: Programming Language :: Python :: 3.11
Classifier: Topic :: Scientific/Engineering :: Hydrology
Requires-Python: >=3.8
License-File: LICENSE
Requires-Dist: numpy
Requires-Dist: pandas
Provides-Extra: optional
Requires-Dist: flopy ; extra == 'optional'
Requires-Dist: pyemu ; extra == 'optional'
Provides-Extra: test
Requires-Dist: pytest ; extra == 'test'
